pump/__init__.py
pump/pump.py
pump.model.JDRX-0.0.2.dist-info/DESCRIPTION.rst
pump.model.JDRX-0.0.2.dist-info/METADATA
pump.model.JDRX-0.0.2.dist-info/RECORD
pump.model.JDRX-0.0.2.dist-info/WHEEL
pump.model.JDRX-0.0.2.dist-info/metadata.json
pump.model.JDRX-0.0.2.dist-info/top_level.txt
